supertransformerlib/__init__.py
supertransformerlib/Attention/__init__.py
supertransformerlib/Attention/feedforward.py
supertransformerlib/Attention/multiheaded_attention.py
supertransformerlib/Basics/__init__.py
supertransformerlib/Basics/head_generation.py
supertransformerlib/Basics/linear.py
supertransformerlib/Basics/local_sample.py
supertransformerlib/Basics/memory_tensor.py
supertransformerlib/Basics/syncronized_tensor.py
supertransformerlib/Core/__init__.py
supertransformerlib/Core/errors.py
supertransformerlib/Core/functions.py
supertransformerlib/Core/kernel.py
supertransformerlib/Core/pad.py
supertransformerlib/Core/reshape_module.py
supertransformerlib/Core/sample_utils.py
supertransformerlib/Core/sparse_utils.py
supertransformerlib/Core/string_util.py
supertransformerlib/NTM/__init__.py
supertransformerlib/NTM/controller.py
supertransformerlib/NTM/errors.py
supertransformerlib/NTM/heads.py
supertransformerlib/NTM/indexer.py
supertransformerlib/NTM/ntm.py
supertransformerlib/NTM/reset.py
supertransformerlib/Preprocessing/__init__.py
supertransformerlib/Preprocessing/flattening.py
supertransformerlib/Preprocessing/preprocess.py
supertransformerlib/Preprocessing/string_scripting.py
supertransformerlib-2.4.0.dist-info/LICENSE.txt
supertransformerlib-2.4.0.dist-info/WHEEL
supertransformerlib-2.4.0.dist-info/METADATA
supertransformerlib-2.4.0.dist-info/RECORD
