Metadata-Version: 2.1
Name: supertransformerlib
Version: 2.4.0
Summary: A set of tools for performing ensemble based supertransformer
Keywords: torch,transformer,transformers
Author-email: Christopher M O'Quinn <chrisoquinn.2@gmail.com>
Requires-Python: >=3.9
Requires-Dist: torch >= 1.11
Requires-Dist: numpy
Requires-Dist: flit
Requires-Dist: pytest ; extra == "doc"
Project-URL: Documentation, https://torch-supertransformerlib.readthedocs.io/en/latest/
Project-URL: Source, https://github.com/smithblack-0/torch-supertransformerlib
Provides-Extra: doc
